{"cameraMode":{"drawMode":0,"name":"Shaded","section":"Shading Mode"},"sceneLighting":true,"audioPlay":false,"sceneViewState":{"showFog":true,"showMaterialUpdate":false,"showSkybox":true,"showFlares":true,"showImageEffects":true,"showParticleSystems":true},"in2DMode":false,"pivot":{"x":0.29273176193237307,"y":0.9004391431808472,"z":-0.22316956520080567},"rotation":{"x":-0.06725925207138062,"y":0.6493497490882874,"z":-0.057817090302705768,"w":-0.7553187012672424},"size":6.836223125457764,"orthographic":false}